package1/__init__.py
package1/add_sub_mult_div.py
package1/main.py
my_new_release_project_aba-0.1.0.dist-info/METADATA
my_new_release_project_aba-0.1.0.dist-info/WHEEL
my_new_release_project_aba-0.1.0.dist-info/top_level.txt
my_new_release_project_aba-0.1.0.dist-info/RECORD
