Metadata-Version: 2.1
Name: my-new-release-project-aba
Version: 0.1.0
Summary: good job
Author: kirill
Author-email: KARum2004@yandex.ru
